{
  "python": "Python",
  "python3": "Python",
  "py": "Python",
  "java": "Java",
  "java 8": "Java",
  "java 11": "Java",
  "javascript": "JavaScript",
  "js": "JavaScript",
  "es6": "JavaScript",
  "typescript": "TypeScript",
  "ts": "TypeScript",
  "c++": "C++",
  "cpp": "C++",
  "c#": "C#",
  "csharp": "C#",
  "go": "Go",
  "golang": "Go",
  "rust": "Rust",
  "sql": "SQL",
  "mysql": "MySQL",
  "postgresql": "PostgreSQL",
  "postgres": "PostgreSQL",
  "mongodb": "MongoDB",
  "mongo": "MongoDB",
  "redis": "Redis",
  "docker": "Docker",
  "kubernetes": "Kubernetes",
  "k8s": "Kubernetes",
  "aws": "AWS",
  "amazon web services": "AWS",
  "gcp": "GCP",
  "google cloud": "GCP",
  "azure": "Azure",
  "microsoft azure": "Azure",
  "react": "React",
  "reactjs": "React",
  "angular": "Angular",
  "angularjs": "Angular",
  "vue": "Vue.js",
  "vuejs": "Vue.js",
  "node": "Node.js",
  "nodejs": "Node.js",
  "express": "Express.js",
  "django": "Django",
  "flask": "Flask",
  "fastapi": "FastAPI",
  "spring": "Spring Boot",
  "spring boot": "Spring Boot",
  "ml": "Machine Learning",
  "machine learning": "Machine Learning",
  "ai": "Artificial Intelligence",
  "artificial intelligence": "Artificial Intelligence",
  "dl": "Deep Learning",
  "deep learning": "Deep Learning",
  "nlp": "NLP",
  "natural language processing": "NLP",
  "cv": "Computer Vision",
  "computer vision": "Computer Vision",
  "tensorflow": "TensorFlow",
  "tf": "TensorFlow",
  "pytorch": "PyTorch",
  "scikit-learn": "Scikit-learn",
  "sklearn": "Scikit-learn",
  "pandas": "Pandas",
  "numpy": "NumPy",
  "scipy": "SciPy",
  "matplotlib": "Matplotlib",
  "seaborn": "Seaborn",
  "tableau": "Tableau",
  "power bi": "Power BI",
  "excel": "Excel",
  "git": "Git",
  "github": "GitHub",
  "gitlab": "GitLab",
  "ci/cd": "CI/CD",
  "jenkins": "Jenkins",
  "linux": "Linux",
  "bash": "Bash",
  "shell": "Shell Scripting",
  "html": "HTML",
  "css": "CSS",
  "sass": "SASS",
  "rest api": "REST API",
  "restful api": "REST API",
  "graphql": "GraphQL",
  "system design": "System Design",
  "microservices": "Microservices",
  "agile": "Agile",
  "scrum": "Scrum",
  "jira": "Jira",
  "unit testing": "Unit Testing",
  "tdd": "TDD",
  "statistics": "Statistics",
  "probability": "Probability"
}